aioonkyo/__init__.py
aioonkyo/common.py
aioonkyo/instruction.py
aioonkyo/message.py
aioonkyo/message_code.py
aioonkyo/parameter.py
aioonkyo/protocol.py
aioonkyo/py.typed
aioonkyo/receiver.py
aioonkyo/status.py
aioonkyo/export/__init__.py
aioonkyo/export/status.py
aioonkyo/export/instruction/__init__.py
aioonkyo/export/instruction/command.py
aioonkyo/export/instruction/query.py
aioonkyo-0.4.0.dist-info/METADATA
aioonkyo-0.4.0.dist-info/WHEEL
aioonkyo-0.4.0.dist-info/licenses/LICENCE
aioonkyo-0.4.0.dist-info/RECORD
