Metadata-Version: 2.4
Name: aioonkyo
Version: 0.4.0
Summary: A library for controlling Onkyo AV receivers.
Project-URL: Homepage, https://github.com/arturpragacz/aioonkyo
Author: Artur Pragacz
License-Expression: GPL-3.0-only
License-File: LICENCE
Keywords: asyncio,eiscp,onkyo,receiver
Classifier: Operating System :: OS Independent
Classifier: Programming Language :: Python :: 3.13
Requires-Python: >=3.13
